{
  "id": 161,
  "jsx": 190,
  "template_name": "Photo|template_154",
  "preview": "generators/previews/USA_Minnesota_DL.jpg",
  "description": "",
  "image1_default": "generators/USA  Missouri Driver License/image1/PHOTODROP.jpg",
  "image2_default": "generators/USA  Missouri Driver License/image2/signature.jpg",
  "image3_default": null,
  "image4_default": null,
  "slug": "dl_minnesota",
  "name": "USA Minnesota Driver License",
  "icon": "generators/USA Minnesota Driver License/icon/mn.png",
  "price": "8.99",
  "image5_default": null,
  "identifier": "dl_minnesota",
  "is_pdf": false,
  "is_active": true,
  "is_compress": true,
  "steps": [
    {
      "id": 636,
      "name": "Step 1",
      "fields": [
        {
          "id": 2248,
          "input_label": "First Name",
          "input_placeholder": "John",
          "input_name": "FN",
          "type": "text",
          "value": null,
          "required": true,
          "regular_expression": null
        },
        {
          "id": 2249,
          "input_label": "Last Name",
          "input_placeholder": "Doe",
          "input_name": "LN",
          "type": "text",
          "value": null,
          "required": true,
          "regular_expression": null
        },
        {
          "id": 2250,
          "input_label": "Middle name (Not necessary!)",
          "input_placeholder": "Lee",
          "input_name": "MN",
          "type": "text",
          "value": null,
          "required": false,
          "regular_expression": null
        },
        {
          "id": 2251,
          "input_label": "Document number",
          "input_placeholder": "A123-123-123-123",
          "input_name": "NUMBER",
          "type": "text",
          "value": null,
          "required": true,
          "regular_expression": null
        },
        {
          "id": 2252,
          "input_label": "Sex (M or F)",
          "input_placeholder": "M",
          "input_name": "SEX",
          "type": "text",
          "value": null,
          "required": true,
          "regular_expression": null
        }
      ]
    },
    {
      "id": 637,
      "name": "Step 2",
      "fields": [
        {
          "id": 2253,
          "input_label": "Date of birth (MM/DD/YYYY)",
          "input_placeholder": "10/16/1986",
          "input_name": "DOB",
          "type": "text",
          "value": null,
          "required": true,
          "regular_expression": null
        },
        {
          "id": 2254,
          "input_label": "Date of issue (MM/DD/YYYY)",
          "input_placeholder": "12/15/2020",
          "input_name": "DOI",
          "type": "text",
          "value": null,
          "required": true,
          "regular_expression": null
        },
        {
          "id": 2255,
          "input_label": "Date of expiry (MM/DD/YYYY)",
          "input_placeholder": "10/16/2024",
          "input_name": "DOE",
          "type": "text",
          "value": null,
          "required": true,
          "regular_expression": null
        }
      ]
    },
    {
      "id": 638,
      "name": "Step 3",
      "fields": [
        {
          "id": 2256,
          "input_label": "Address",
          "input_placeholder": "123 Anywhere Street",
          "input_name": "ADDRESS",
          "type": "text",
          "value": null,
          "required": true,
          "regular_expression": null
        },
        {
          "id": 2257,
          "input_label": "City",
          "input_placeholder": "Anytown",
          "input_name": "CITY",
          "type": "text",
          "value": null,
          "required": true,
          "regular_expression": null
        },
        {
          "id": 2258,
          "input_label": "Zip Code",
          "input_placeholder": "12345-0000",
          "input_name": "INDEX",
          "type": "text",
          "value": null,
          "required": true,
          "regular_expression": null
        }
      ]
    },
    {
      "id": 639,
      "name": "Step 4",
      "fields": [
        {
          "id": 2259,
          "input_label": "Height (in inches!)",
          "input_placeholder": "068 IN",
          "input_name": "HGT",
          "type": "text",
          "value": "068 IN",
          "required": true,
          "regular_expression": null
        },
        {
          "id": 2260,
          "input_label": "Weight",
          "input_placeholder": "160 lb",
          "input_name": "WGT",
          "type": "text",
          "value": "160 lb",
          "required": true,
          "regular_expression": null
        },
        {
          "id": 2261,
          "input_label": "Eye Color Code",
          "input_placeholder": "BRO",
          "input_name": "EYE",
          "type": "text",
          "value": null,
          "required": true,
          "regular_expression": null
        }
      ]
    },
    {
      "id": 640,
      "name": "Step 5",
      "fields": [
        {
          "id": 2262,
          "input_label": "Result image Type (Photo, Scan, Print)",
          "input_placeholder": "Photo",
          "input_name": "BACKGROUND",
          "type": "text",
          "value": null,
          "required": false,
          "regular_expression": null
        },
        {
          "id": 2263,
          "input_label": "Background number (1 - 30)",
          "input_placeholder": "1",
          "input_name": "BACKGROUND_NUMBER",
          "type": "text",
          "value": null,
          "required": false,
          "regular_expression": "(30|[12][0-9]|[1-9])"
        },
        {
          "id": 2264,
          "input_label": "Photo",
          "input_placeholder": "Upload your photo (JPG or PNG)",
          "input_name": "image1",
          "type": "file",
          "value": null,
          "required": false,
          "regular_expression": null
        },
        {
          "id": 2265,
          "input_label": "Signature",
          "input_placeholder": "Upload your photo (JPG or PNG)",
          "input_name": "image2",
          "type": "file",
          "value": null,
          "required": false,
          "regular_expression": null
        }
      ]
    }
  ],
  "name_default": "USA Minnesota Driver License"
}